archivo/__init__.py
archivo/archivo.py
archivo/cli.py
archivo-0.1.0.dist-info/AUTHORS.rst
archivo-0.1.0.dist-info/LICENSE
archivo-0.1.0.dist-info/METADATA
archivo-0.1.0.dist-info/WHEEL
archivo-0.1.0.dist-info/entry_points.txt
archivo-0.1.0.dist-info/top_level.txt
archivo-0.1.0.dist-info/RECORD
