Metadata-Version: 2.1
Name: archivo
Version: 0.1.0
Summary: File the files
Home-page: https://github.com/rasmuse/archivo
Author: Rasmus Einarsson
Author-email: mr@rasmuseinarsson.se
License: MIT license
Keywords: archivo
Platform: UNKNOWN
Classifier: Development Status :: 2 - Pre-Alpha
Classifier: Intended Audience :: Developers
Classifier: License :: OSI Approved :: MIT License
Classifier: Natural Language :: English
Classifier: Programming Language :: Python :: 3
Requires-Dist: Click (>=7.0)
